LICENSE
MANIFEST.in
README.rst
setup.cfg
setup.py
databutton/__init__.py
databutton/cli.py
databutton/version.py
databutton/helpers/__init__.py
databutton/helpers/parse.py
databutton/server/__init__.py
databutton/server/processes.py
databutton/server/server.py
databutton_cli.egg-info/PKG-INFO
databutton_cli.egg-info/SOURCES.txt
databutton_cli.egg-info/dependency_links.txt
databutton_cli.egg-info/entry_points.txt
databutton_cli.egg-info/requires.txt
databutton_cli.egg-info/top_level.txt